Metadata-Version: 2.1
Name: tabout
Version: 1.0.6
Summary: Create sound and/or slack notifications within your script
Home-page: https://github.com/daverbuj/Tabout
Author: Dan Averbuj
Author-email: dan.averbuj@gmail.com
License: UNKNOWN
Platform: UNKNOWN
